admin_search_plus/__init__.py
admin_search_plus/admin.py
admin_search_plus/mixins.py
admin_search_plus/__pycache__/__init__.cpython-37.pyc
admin_search_plus/templates/admin/search_form.html
admin_search_plus/templatetags/__init__.py
admin_search_plus/templatetags/admin_search_plus.py
admin_search_plus-0.3.1.dist-info/LICENSE
admin_search_plus-0.3.1.dist-info/METADATA
admin_search_plus-0.3.1.dist-info/WHEEL
admin_search_plus-0.3.1.dist-info/top_level.txt
admin_search_plus-0.3.1.dist-info/RECORD
