Metadata-Version: 2.1
Name: admin-search-plus
Version: 0.3.1
Summary: Mixin for Django's admin objects to enhance searching by limiting searchable fields
Home-page: https://github.com/Lenders-Cooperative/django-admin-search-plus
Author: David Graves
Author-email: dgraves@gravitate-us.com
License: bsd-3-clause
Download-URL: https://github.com/Lenders-Cooperative/django-admin-search-plus/archive/v_03.tar.gz
Keywords: django admin search
Platform: any
Classifier: Environment :: Web Environment
Classifier: Framework :: Django
Classifier: Intended Audience :: Developers
Classifier: Operating System :: OS Independent
Classifier: Programming Language :: Python
Classifier: Programming Language :: Python :: 3
Requires-Python: >=3.6
License-File: LICENSE
Requires-Dist: Django (>=2.2.9)
